[{"id":2,"name":"Shika","coordinates":{"x":12.0,"y":12},"creationDate":1677523740958,"oscarsCount":3,"genre":"SCIENCE_FICTION","mpaaRating":"NC_17","director":{"name":"Max","birthday":"2003-10-29T00:00+03:00[Europe/Moscow]","eyeColor":"WHITE","location":{"x":12.0,"y":12.0,"z":12.0}}},{"id":3,"name":"qwfgsdg","coordinates":{"x":123.0,"y":123},"creationDate":1678534052989,"oscarsCount":12,"genre":"COMEDY","mpaaRating":"G","director":{"name":"dhbtdfghd","birthday":"2004-03-01T00:00+03:00[Europe/Moscow]","eyeColor":"GREEN","location":{"x":123.0,"y":123.0,"z":123.0}}},{"id":4,"name":"Shika","coordinates":{"x":123.0,"y":123},"creationDate":1678620242513,"oscarsCount":5,"genre":"FANTASY","mpaaRating":"R","director":{"name":"hrherheh","birthday":"2004-03-01T00:00+03:00[Europe/Moscow]","eyeColor":"GREEN","location":{"x":123.0,"y":123.0,"z":123.0}}},{"id":5,"name":"LondonMall","coordinates":{"x":123.0,"y":123},"creationDate":1678622410542,"oscarsCount":10,"genre":"COMEDY","mpaaRating":"G","director":{"name":"Max","birthday":"2004-03-01T00:00+03:00[Europe/Moscow]","eyeColor":"YELLOW","location":{"x":12.0,"y":12.0,"z":12.0}}}]